CodeForSubmission/TestBench.sv

// Mark W Welker
// Generic Test bench It drives only clock and reset.


module TestExe  (Clk,nReset);

	output logic Clk,nReset; // we are driving these signals from here. 

	initial begin
		Clk = 0;
		nReset = 1;
	#5 nReset = 0;
	#5 nReset = 1;
	end
	
	always  #5 Clk = ~Clk;

	
	endmodule

CopyOfLocalModelSimProjectFolder/Excutre/ExcutionEngin.sv
///////////////////////////////////////
// FILE: ExcutionEngin.sv            //
// LastEdited 11/2/2021              //
// Created by: JESUS RIVERA III      //
///////////////////////////////////////
//	On Reset, loads in 1 instuctions. Loads in next instuction
//	in place of instuction that was last ran after that.
//
//
///////////////////////////////////////
// opCode Definition 32'h xx_xx_xx_xx
//					operation_dest_src1_src2
// 	Address is determined by dest, src1, or src2. If src1 is 0004,
//	then Adress will translate that to a 12 bit 000000000004
//
module Execution (Clk,InstructDataOut,MemDataOut,ExeDataOut, address, nRead,nWrite, nReset);
   parameter  FetchInstuction = 1;
   parameter  DecodeInstuction= 2;
   parameter  ReadInstuction = 3;
   parameter  ExcuteInstruction = 4;
   parameter  Clear = 5;

   //opCode instuctions
   parameter  Stop = 8'h FF;  //Stop the processer
   parameter matrixAdd = 8'h 01;
   parameter matrixSub = 8'h 02;
   parameter matrixTranspose = 8'h 03;
   parameter matrixScale = 8'h 04;
   parameter matrixScaleImmediate = 8'h 05;
   parameter intAdd = 8'h 10;
   parameter intSub = 8'h 11;
   parameter intMultiply = 8'h 12;
   parameter intDiv = 8'h 13;
   //Extra for expanding operations
   //parameter Extra1 = 8'h A1;
   //parameter Extra2 = 8'h A2;
   //parameter Extra3 = 8'h A3;


	output logic nRead,nWrite;
	output logic [15:0] address;
	output logic [255:0] ExeDataOut;
	input logic nReset,Clk;
	input logic [255:0] InstructDataOut;
	input logic [255:0] MemDataOut;
	logic [7:0] clkCounter;	//counts amount of clock cycles for timing
	logic complete; //Unused for now, planed use in final project is to recive complete bit from ALU's
	reg [3:0] currentOperation;

	reg [7:0] PC;	//Program counter, counts which instruction is on
	reg [31:0] opCode;	//could just use specific bits in opCode, but breaking it into other regs makes for easier reading and logic
	reg [7:0] operation;
	reg [7:0] destAddress;
	reg [7:0] src1Address;
	reg [7:0] src2Address;
	///////////////////////////////////////////////////////////////////
	// Sudo ALU code. A ALU should be doing this in the project but
	// for this asignment it is done inside the excution since the ALU
	// Doesnt exist yet.
	reg [255:0] Result;
	reg [255:0] src1Data;
	reg [255:0] src2Data;

	//////////////////////////////////////
	////////RESET CONDITION///////////////
	//////////////////////////////////////


	always_ff @ ( negedge nReset or posedge Clk) begin

		if (nReset == 0) begin   //Reset case
			nRead <= 1;
			nWrite <= 1;
			ExeDataOut <= 0;
			clkCounter <= 0;
			complete <= 0;
			PC <= 0;
         currentOperation <= 0;
		end
   end

   always_ff @(posedge Clk) begin

      if (nReset != 0 && complete == 0) begin //load instuction in not compleate

         if (clkCounter == 0) begin //Sets to get instcutins
            currentOperation = FetchInstuction;
         end

         case (currentOperation)
            FetchInstuction: begin
               case (clkCounter)
                  0: begin //Prepares to get instuction data
                     nRead = 0;
                     nWrite = 1;
                     address = 16'h 8000 + PC;
                  end
                  2: opCode = InstructDataOut;  //Gets instuction data
                  3: begin //Sets for next operation
                     nRead = 1;
                     currentOperation = DecodeInstuction;
                     clkCounter = 0;
                  end
               endcase
               clkCounter++;
            end

            DecodeInstuction: begin       //Breakes opCode into more readable chunks
               operation = opCode[31:24];
               destAddress = opCode[23:16];
               src1Address = opCode[15:8];
               src2Address = opCode[7:0];
               currentOperation = ExcuteInstruction;
            end

            ExcuteInstruction: begin
               case (operation)
                  Stop: $stop;

                  matrixAdd:begin
                     //nothing yet
                  end

                  matrixSub:begin
                     //nothing yet
                  end

                  matrixTranspose:begin
                     //nothing yet
                  end

                  matrixScale:begin
                     //nothing yet
                  end

                  matrixScaleImmediate:begin
                     //nothing yet
                  end

                  intAdd:begin
                     case (clkCounter)
                        1: begin //prepare to get src1 data
                           nRead = 0;
                           address = 16'h 0000 + src1Address;
                        end
                        3: begin    //Get src1 data and prepare to get src2 data
                           src1Data = MemDataOut;
                           address = 16'h 0000 + src2Address;
                        end
                        5: begin    //Get src2 Data and prepare to write to Destination
                           src2Data = MemDataOut;
                           nRead = 1;
                           address = 16'h 0000 + destAddress;
                        end
                        6:begin  //Computation and put out data
                           Result = src1Data + src2Data;
                           ExeDataOut = Result;
                           nWrite = 0;
                        end
                     8:begin  //end add case
                        nWrite = 1;
                        PC++;
                        clkCounter = 0;   //Sets to get the next instruction
                        ExeDataOut = 256'b x;   //Stop outputing data
                        $display ("Sorce 1:%d\n",src1Data);
                        $display ("Sorce 2:%d\n",src2Data);
                        $display ("Result is :%d\n",Result);
                     end//8
                  endcase//intAdd

                  if (clkCounter != 0) begin
                     clkCounter++;
                  end
               end

               intSub: begin
                  //nothing yet
               end

               intMultiply:begin
                  //nothing yet
               end

               intDiv:begin
                  //nothing yet
               end //intDiv
            endcase//operation
         end //ExcuteInstruction
         default: ;//default case does nothing
      endcase //currentOperation
   end ////(nReset != 0 && complete == 0)
end //always_ff @(posedge Clk)

endmodule

MainMemory.sv
////////////////////////////////////////////////////////////////////
// FILE: MainMemory.sv                                            //
// LastEdited 10/15/2021                                          //
// Created by: JESUS RIVERA III                                   //
////////////////////////////////////////////////////////////////////
//                           Internal Adress Decodeing            //
// Address [15:12] (4bits) Module select                          //
// Address [11-0] (12bits) are the memory Location                //
// EX: adress =0000_000000000101 woud be                          //
//     [Main memory]_[Matrix 5]_[specifc matrix Location]         //
//     address = 0000_000000001001 woud be                        //
//     [Main memory]_[Matrix 7]                                   //
//Memory Structure!!!!//////////////////////////////////////////////
// mainMemArray [0] = matrix 1
// mainMemArray [1] = matrix 2
// mainMemArray [2] = matrix Result 1
// mainMemArray [3] = matrix Result 2
// mainMemArray [4] = matrix Result 3
// mainMemArray [5] = matrix Result 4
// mainMemArray [6] = matrix Result 5
// mainMemArray [7] = matrix Result 6
// mainMemArray [8] = Interger Data 1
// mainMemArray [9] = Interger Data 2
// mainMemArray [10] = Interger Result
// mainMemArray [11] = Interger Result
// mainMemArray [12] = Interger Result
// mainMemArray [13] = Interger Result
// mainMemArray [14] = Extra
// mainMemArray [15] = Extra

//Main Mem
module MainMemory(Clk, DataOut,DataIn, address, nRead, nWrite, nReset);

   parameter matrixMemory0 = 256'h0004_000c_0004_0022_0007_0006_000b_0009_0009_0002_0008_000d_0002_000f_0010_0003;
   parameter matrixMemory1 = 256'h0017_002d_0043_0016_0007_0006_0004_0001_0012_0038_000d_000c_0003_0005_0007_0009;



   input logic nRead, nWrite, nReset, Clk;
   input logic [15:0] address;
   input logic [255:0] DataIn;
   output logic [255:0] DataOut;
   int typeMemAccess,memLocation,row,column;
   reg [3:0][3:0][15:0]mainMemArray[15:0];  //16 4x4x16 bit arrays total of 256bits
   always @ (address) begin
      memLocation = address[11:0];
   end

   // allows for simtnous read and write access, I think this is neccesary for
   //   the pipe lineing I plan for the project. Can easily be changed to not
   //   allow both read and write at the same time.
   always_ff @ ( negedge nReset or posedge Clk) begin
      if (nReset == 0) begin
         mainMemArray[0] <= matrixMemory0;
		 mainMemArray[1] <= matrixMemory1;
         DataOut <= 0;
      end

      if (address[15:12] == 0 && nReset != 0 ) begin
         //read Commands
         if (nRead == 0) begin
            //Read data out of a chosen Matrix
            DataOut <= mainMemArray[memLocation];
         end
         //Write commands
         if (nWrite == 0) begin
               mainMemArray[memLocation] <= DataIn;
         end
      end //if
   end //always
endmodule

InstructionMemory.sv
/////////////////////////////////////////
// FILE: MemModual.sv                  //
// LastEdited 10/14/2021               //
// Created by: JESUS RIVERA III        //
/////////////////////////////////////////
//
// The address bus is large enough that each module can contain a local address decode. This will save on multiple enables.
// for now have each module dedicated to an address line. A more generic solution would be to decode the upper bits and have a specific range. Use all 4 address bits [15:12] in decode.
// bits 15:12 are used to memory map each peripheral

// 0 = main memory
// 1 = Instruction memory
// 2 = Matrix ALU
// 3 = Integer ALU
// 4 = Internal Register
// 5 = execution engine

// bit 11-0 are for addressing inside each unit.
// nWrite = 0 means databus is being written into on the falling edge of write
// nRead = 0 means it is expected to drive the databus while this signal is low and the address is correct until the nRead goes high independent of address bus.

// instruction: OPcode :: dest :: src1 :: src2 Each section is 8 bits.
// Stop::FFh::00::00::00
// MMult::00h::Reg/mem::Reg/mem::Reg/mem
// Madd::01h::Reg/mem::Reg/mem::Reg/mem
// Msub::02h::Reg/mem::Reg/mem::Reg/mem
// Mtranspose::03h::Reg/mem::Reg/mem::Reg/mem
// MScale::04h::Reg/mem::Reg/mem::Reg/mem
// MScaleImm::05h:Reg/mem::Reg/mem::Immediate
// IntAdd::10h::Reg/mem::Reg/mem::Reg/mem
// IntSub::11h::Reg/mem::Reg/mem::Reg/mem
// IntMult::12h::Reg/mem::Reg/mem::Reg/mem
// IntDiv::13h::Reg/mem::Reg/mem::Reg/mem



//Instruction Mem
module InstructionMemory(Clk, DataOut, address, nRead, nReset);
   input logic nRead, nReset, Clk;
   input logic [15:0] address;
   output logic [255:0] DataOut;
   reg [31:0]instructMem[9:0];


   parameter Instruct1 = 32'h 01_02_00_01;  // ADD matrix at memory location 0 to memory location 1 store in memory location 2
   parameter Instruct2 = 32'h 02_03_00_01;  //Stop
   parameter Instruct3 = 32'h 00_04_00_01;
   //Transpose the result from step 1 store in memory
   parameter Instruct4 = 32'h 03_05_00_00;
   //Scale the result in step 3 by the result from step 2 store in a matrix register
   parameter Instruct5 = 32'h 04_06_00_09;
   //Multiply the result from step 4 by the result in step 3, store in memory.
   parameter Instruct6 = 32'h 05_07_00_64;
   //Multiply memory location 0 to location 1. Store it in memory location 0A
   parameter Instruct7 = 32'h FF_0A_00_01;
   //Subtract Memory 01 from memory location 0A and store it in a register
   parameter Instruct8 = 32'h 11_0A_01_81;
   //Divide Memory location 0A by the register in step 8 and store it in location B
   parameter Instruct9 = 32'h 13_0B_0A_81;
   //STOP
   parameter Instruct10 = 32'h ff_ff_ff_ff;
   //Sets the Address select for Instuction Memory Modual
   parameter InstuctionSelect = 4'b 1000;
   //////////////////////////////////////////////////////////////////
   always @ ( negedge nReset) begin
      if (nReset == 0) begin
         instructMem[0] <= Instruct1;
         instructMem[1] <= Instruct2;
         instructMem[2] <= Instruct3;
         instructMem[3] <= Instruct4;
         instructMem[4] <= Instruct5;
         instructMem[5] <= Instruct6;
         instructMem[6] <= Instruct7;
         instructMem[7] <= Instruct8;
         instructMem[8] <= Instruct9;
         instructMem[9] <= Instruct10;
      end
   end

   always_ff @ (posedge Clk) begin
      if (address[15:12] == InstuctionSelect && nRead == 0) begin   //If The InsturctMem is being commanded by the address
         DataOut <= instructMem[address[11:0]];
      end
   end
endmodule

CodeForSubmission/Top.sv
///////////////////////////////

// Mark W. Welker
// HDL 4321 Spring 2021
// execution engine assignment top module
//
//
//
module top ();

logic [255:0] InstructDataOut;
logic [255:0] MemDataOut;
logic [255:0] ExeDataOut;
logic nRead,nWrite,nReset,Clk;
logic [15:0] address;

InstructionMemory  U1(Clk,InstructDataOut, address, nRead,nReset);

MainMemory  U2(Clk,MemDataOut,ExeDataOut, address, nRead,nWrite, nReset);

Execution  U3(Clk,InstructDataOut,MemDataOut,ExeDataOut, address, nRead,nWrite, nReset);

TestExe  UTest(Clk,nReset);

  initial begin //. setup to allow waveforms for edaplayground
   $dumpfile("dump.vcd");
   $dumpvars(1);
 end

endmodule

CopyOfLocalModelSimProjectFolder/Excutre/dump.vcd
$date
	Thu Nov  4 18:06:33 2021
$end
$version
	ModelSim Version 2021.1
$end
$timescale
	1ps
$end

$scope module top $end
$var reg 256 ! InstructDataOut [255:0] $end
$var reg 256 " MemDataOut [255:0] $end
$var reg 256 # ExeDataOut [255:0] $end
$var reg 1 $ nRead $end
$var reg 1 % nWrite $end
$var reg 1 & nReset $end
$var reg 1 ' Clk $end
$var reg 16 ( address [15:0] $end
$upscope $end
$enddefinitions $end
#0
$dumpvars
bx !
bx "
bx #
x$
x%
1&
0'
bx (
$end
#5
1'
0&
b0 "
b0 #
1%
1$
#10
0'
1&
#15
1'
b1000000000000000 (
0$
#20
0'
#25
1'
b10000000000100000000000000001 !
#30
0'
#35
1'
#40
0'
#45
1'
1$
#50
0'
#55
1'
#60
0'
#65
1'
b0 (
0$
#70
0'
#75
1'
b100000000000000110000000000000001000000000000100010000000000000011100000000000001100000000000001011000000000000100100000000000010010000000000000010000000000000100000000000000011010000000000000010000000000000111100000000000100000000000000000011 "
#80
0'
#85
1'
b1 (
#90
0'
#95
1'
b10111000000000010110100000000010000110000000000010110000000000000011100000000000001100000000000000100000000000000000100000000000100100000000000111000000000000000110100000000000011000000000000000011000000000000010100000000000001110000000000001001 "
#100
0'
#105
1'
b10 (
1$
#110
0'
#115
1'
0%
b11011000000000011100100000000010001110000000000111000000000000000111000000000000011000000000000001111000000000000101000000000000110110000000000111010000000000001010100000000000110010000000000000101000000000001010000000000000101110000000000001100 #
#120
0'
#125
1'
#130
0'
#135
1'
bx #
1%
#140
0'
#145
1'
b1000000000000001 (
0$
#150
0'
#155
1'
b11111111000000000000000000000000 !
#160
0'
#165
1'
#170
0'
#175
1'
1$
